flawful/__init__.py
flawful/german.py
flawful/utils.py
flawful/data/example1/input_notes.txt
flawful/data/example1/known_no_audio.txt
flawful/data/example1/okaylist_LA.txt
flawful/data/example1/okaylist_LB.txt
flawful/data/example1/okaylist_LC.txt
flawful/data/example1/reflist_LA.txt
flawful/data/example1/reflist_LB.txt
flawful/data/example1/reflist_LC.txt
flawful/data/example1/audio/DiB/DiB-D01_Handy.mp3
flawful/data/example1/audio/DiB/DiB-D01_Italien.mp3
flawful/data/example1/audio/DiB/DiB-D01_acht.mp3
flawful/data/example1/audio/DiB/DiB-D01_bleiben.mp3
flawful/data/example1/audio/DiB/DiB-D01_ich bin Student.mp3
flawful/data/example1/audio/DiB/DiB-D01_ich komme aus den USA.mp3
flawful/data/example1/audio/DiB/DiB-D01_kommen aus.mp3
flawful/data/example1/audio/DiB/DiB-D01_rosa.mp3
flawful/data/example1/audio/DiB/DiB-D01_was ist deine Handynummer.mp3
flawful/data/example1/audio/DiB/DiB-D02_Professor.mp3
flawful/data/example1/audio/DiB/DiB-D02_Student.mp3
flawful/data/example1/audio/DiB/DiB-D02_Vorlesungsverzeichnis.mp3
flawful/data/example1/audio/DiB/DiB-D02_sprechen.mp3
flawful/data/example1/audio/DiB/DiB-D02_welcher.mp3
flawful/data/example1/audio/DiB/DiB-D03_Brötchen.mp3
flawful/data/example1/audio/DiB/DiB-D03_Gericht.mp3
flawful/data/example1/audio/DiB/DiB-D03_Joghurt.mp3
flawful/data/example1/audio/DiB/DiB-D03_trinken.mp3
flawful/data/example1/audio/DiB/DiB-D04_Komödie.mp3
flawful/data/example1/audio/DiB/DiB-D04_du bist ja verrückt.mp3
flawful/data/example1/audio/DiB/DiB-D04_teuer.mp3
flawful/data/example1/audio/DiB/DiB-D04_verrückt.mp3
flawful/data/example1/audio/DiB/DiB-D05_Familienmitglied.mp3
flawful/data/example1/audio/DiB/DiB-D05_Geschwister.mp3
flawful/data/example1/audio/DiB/DiB-D05_Verwandte.mp3
flawful/data/example1/audio/DiB/DiB-D05_verrückt.mp3
flawful/data/example1/audio/DiB/DiB-D06_helfen.mp3
flawful/data/example1/audio/DiB/DiB-D06_teuer.mp3
flawful/data/example1/audio/DiB/DiB-D07_Gesicht.mp3
flawful-0.2.0.dist-info/LICENSE.txt
flawful-0.2.0.dist-info/LICENSE_GPL_v3.txt
flawful-0.2.0.dist-info/METADATA
flawful-0.2.0.dist-info/WHEEL
flawful-0.2.0.dist-info/top_level.txt
flawful-0.2.0.dist-info/RECORD
