Metadata-Version: 2.2
Name: flawful
Version: 0.2.0
Summary: Tools for flashcards, audio files, and word lists for language learning.
Author-email: Ray Griner <rgriner_fwd@outlook.com>
License: ---------------------------------------
Keywords: flashcards,language learning,audio
Classifier: Programming Language :: Python :: 3
Classifier: Operating System :: OS Independent
Classifier: Development Status :: 3 - Alpha
Classifier: Natural Language :: German
License-File: LICENSE.txt
License-File: LICENSE_GPL_v3.txt
Requires-Dist: numpy
Requires-Dist: pandas
